setup.py
gaussian_binomial_distributions_tushcathy/Binomialdistribution.py
gaussian_binomial_distributions_tushcathy/Gaussiandistribution.py
gaussian_binomial_distributions_tushcathy/Generaldistribution.py
gaussian_binomial_distributions_tushcathy/__init__.py
gaussian_binomial_distributions_tushcathy.egg-info/PKG-INFO
gaussian_binomial_distributions_tushcathy.egg-info/SOURCES.txt
gaussian_binomial_distributions_tushcathy.egg-info/dependency_links.txt
gaussian_binomial_distributions_tushcathy.egg-info/not-zip-safe
gaussian_binomial_distributions_tushcathy.egg-info/top_level.txt