Metadata-Version: 1.0
Name: gaussian-binomial-distributions-tushcathy
Version: 0.1
Summary: Gaussian and binomial distributions
Home-page: UNKNOWN
Author: Catherine Tushabe
Author-email: tushcathy@gmail.com
License: UNKNOWN
Platform: UNKNOWN
